sagemaker_connection_magics_jlextension/__init__.py
sagemaker_connection_magics_jlextension/labextension/package.json
sagemaker_connection_magics_jlextension/labextension/schemas/@amzn/sagemaker-connection-magics-jlextension/package.json.orig
sagemaker_connection_magics_jlextension/labextension/schemas/@amzn/sagemaker-connection-magics-jlextension/plugin.json
sagemaker_connection_magics_jlextension/labextension/static/181.a3ea4815b59b6923e81a.js
sagemaker_connection_magics_jlextension/labextension/static/562.96bff51ed9c8fcc3057f.js
sagemaker_connection_magics_jlextension/labextension/static/775.cb8565436785ab16e832.js
sagemaker_connection_magics_jlextension/labextension/static/799.96b3234f88efc1dbad60.js
sagemaker_connection_magics_jlextension/labextension/static/919.8a223dcb13314e78753c.js
sagemaker_connection_magics_jlextension/labextension/static/919.8a223dcb13314e78753c.js.LICENSE.txt
sagemaker_connection_magics_jlextension/labextension/static/remoteEntry.2f54443fd194c686a833.js
sagemaker_connection_magics_jlextension/labextension/static/style.js
sagemaker_connection_magics_jlextension/labextension/static/third-party-licenses.json
sagemaker_data_explorer/labextension/package.json
sagemaker_data_explorer/labextension/static/181.e43f2bc0b7c9fd78e814.js
sagemaker_data_explorer/labextension/static/529.6b3f11289da4122d7b9e.js
sagemaker_data_explorer/labextension/static/remoteEntry.d07f2582bf9dfcb40144.js
sagemaker_data_explorer/labextension/static/style.js
sagemaker_data_explorer/labextension/static/third-party-licenses.json
sagemaker_jupyter_server_extension/__init__.py
sagemaker_jupyter_server_extension/connection_handler.py
sagemaker_jupyter_server_extension/connections_handler.py
sagemaker_jupyter_server_extension/creds_handlers.py
sagemaker_jupyter_server_extension/debugging_info_handler.py
sagemaker_jupyter_server_extension/env_handlers.py
sagemaker_jupyter_server_extension/extension.py
sagemaker_jupyter_server_extension/identity.py
sagemaker_studio_dataengineering_extensions-1.3.2.dist-info/METADATA
sagemaker_studio_dataengineering_extensions-1.3.2.dist-info/WHEEL
sagemaker_studio_dataengineering_extensions-1.3.2.dist-info/licenses/LICENSE
sagemaker_studio_dataengineering_extensions-1.3.2.dist-info/licenses/NOTICE
sagemaker_studio_dataengineering_extensions-1.3.2.dist-info/RECORD
