Metadata-Version: 2.4
Name: sagemaker-studio-dataengineering-extensions
Version: 1.3.2
Summary: A python Package to enhance experience of SageMaker Unified Studio
Author: Amazon Web Services
Maintainer: sagemaker-unified-studio
License-Expression: Apache-2.0
License-File: LICENSE
License-File: NOTICE
Keywords: AWS,Amazon,Data Engineering,SageMaker,SageMaker Unified Studio
Classifier: Framework :: Jupyter
Classifier: Framework :: Jupyter :: JupyterLab
Classifier: Framework :: Jupyter :: JupyterLab :: 4
Classifier: Framework :: Jupyter :: JupyterLab :: Extensions
Classifier: Framework :: Jupyter :: JupyterLab :: Extensions :: Prebuilt
Classifier: License :: OSI Approved :: Apache Software License
Classifier: Programming Language :: Python
Classifier: Programming Language :: Python :: 3
Classifier: Programming Language :: Python :: 3.11
Classifier: Programming Language :: Python :: 3.12
Requires-Python: >=3.11
Requires-Dist: aiobotocore<3,>=2.9
Requires-Dist: async-lru
Requires-Dist: async-timeout
Requires-Dist: aws-embedded-metrics
Requires-Dist: boto3
Requires-Dist: jupyter-scheduler<3,>=2.7.0
Requires-Dist: jupyter-server<3,>=1.6
Requires-Dist: pydantic
Requires-Dist: pytest
Requires-Dist: requests
Requires-Dist: sagemaker-studio>=1.0.16
Requires-Dist: schedule
